{
  "reportId": "12994",
  "title": "Man observes creature walking across road.",
  "date": "2005-11-03",
  "timestamp": 1130976000,
  "observed": "I was traveling southeast from crownpoint nm, on the eastern part of the Navajo Reservation. i was headed home as i was going through a small canyon (pass) in the head lights of the vehicle i observed a animal traveling east to west across the high way, it appears to about 6ft. tall and big, it was walking on two legs and went into a small gully i pulled the vehicle around and shine the light up the gully and i could not relocate the animal. due to the darkness and only seeing it through the head lights i could not make out the hair color it appeared dark. i know the differents between deer and other animals and it was not one of them, i could not explain what i've seen. ",
  "classification": "Class A",
  "county": "McKinley",
  "state": "New Mexico",
  "latitude": 35.58565,
  "longitude": -107.9978,
  "location": "-107.9978,35.58565",
  "location_details": "about 10 miles southeast of crowpoint nm on highway # 9 i belive it a bia road",
  "temperature_high": 60.09,
  "temperature_mid": 49.7,
  "temperature_low": 39.31,
  "dew_point": 26.82,
  "humidity": 0.39,
  "cloud_cover": 0.15,
  "moon_phase": 0.06,
  "precip_intensity": 0,
  "precip_probability": 0,
  "pressure": 1015.67,
  "summary": "Partly cloudy starting in the afternoon, continuing until evening.",
  "uv_index": 4,
  "visibility": 9.97,
  "wind_bearing": 214,
  "wind_speed": 5.95
}