{
  "reportId": "4975",
  "title": "Sighting at Camp Oyo Boy Scout Camp on Rt. 125",
  "date": "1977-10-31",
  "timestamp": 247104000,
  "observed": "While taking a break during a hike back from the Lou Wetzel cabin, we were sitting at a picnic area just below the Clark cabin when we seen a creature walking upright on it's hind legs with long brown hair and piercing green eyes. We was only able to see from the waist up due to the brush.",
  "classification": "Class B",
  "county": "Scioto",
  "state": "Ohio",
  "latitude": 38.77727,
  "longitude": -83.18179,
  "location": "-83.18179,38.77727",
  "location_details": "Camp Oyo Boy Scout Camp on Rt. 125",
  "temperature_high": 65.25,
  "temperature_mid": 59.28,
  "temperature_low": 53.31,
  "dew_point": 42.99,
  "humidity": 0.59,
  "cloud_cover": 0.77,
  "moon_phase": 0.64,
  "precip_intensity": 0.0003,
  "precip_probability": 0.16,
  "precip_type": "rain",
  "pressure": 1020.66,
  "summary": "Mostly cloudy throughout the day.",
  "uv_index": 2,
  "visibility": 8.5,
  "wind_bearing": 148,
  "wind_speed": 8.27
}