{
  "reportId": "28418",
  "title": "Woman remembers two visual encounters near Williston",
  "date": "1991-08-14",
  "timestamp": 682128000,
  "observed": "IT WAS AROUND AUGUST, SEE AS THERE WAS A STORM COMING IN, THIS WAS WAS AROUND 1991 ME AND ONE OF MY SIS WAS GOING TO GET THE OTHER ONE, WE WERE TRAVELING ST RD 121 DOWN FROM GOLF CLUB WHEN WE CAME OVER THE HILL THERE WERE FOUR, RANGING FROM 9 FOOT TO7 FOOT AND THE SMALLEST WAS AROUND 5 FOOT  WALKING ACROSS THE ROAD.  I BELIEVE THEY WERE MOVING BECAUSE OF THE STORM THEY WHERE HEADED EAST AT WITCH TIME WAS A WOODED AREA. THERE WAS ALSO ANOTHER TIME WHEN THEY WERE SEEN AND IT WAS IN THE CITY OF WILLISTON  I WAS WORKING FOR THE CITY AND WENT FOR A CALL AND IT WAS  IN THE DUMPSTER AT THE TOP OF THE HILL, THIS ONE WAS A YOUNG ONE, HE WAS ABOUT 5 FOOT TALL, WHEN THE TRUCK LIGHTS HIT HIM IT RAN",
  "classification": "Class A",
  "county": "Levy",
  "state": "Florida",
  "latitude": 29.39384,
  "longitude": -82.44225,
  "location": {
    "longitude": -82.44225,
    "latitude": 29.39384
  },
  "location_details": "ABOUT 7 MILLS OUT OF WILLISTON ST RD 121",
  "temperature": {
    "high": 90.76,
    "mid": 82.12,
    "low": 73.48
  },
  "dew_point": 69.38,
  "humidity": 0.74,
  "cloud_cover": 0.48,
  "moon_phase": 0.17,
  "precip_intensity": 0.0217,
  "precip_probability": 1,
  "precip_type": "rain",
  "pressure": 1017.1,
  "summary": "Heavy rain overnight.",
  "uv_index": 8,
  "visibility": 7.54,
  "wind_bearing": 226,
  "wind_speed": 4.4
}