{
  "reportId": "24854",
  "title": "Dusk sighting by two teenagers participating in the Youth Deer Hunt near Wolverine",
  "date": "2008-10-16",
  "observed": "Me and my freind alan where walking back out of green timbers after a day of deer hunting it was about 7 or 8 when w both seen it at the same time it was about 6 to 8 feet tall and 300 to 500 pounds it just simply walked out of the woods walking to the corn feild got about half way to the corn and stopped looked at us and turned around and walked right back in the woods dident make a sound not even a twig broke when we got up there to ware he was he was gone no sign and no noise there was nothing",
  "classification": "Class A",
  "county": "Cheboygan",
  "state": "Michigan",
  "location": "-84.425,45.1475",
  "location_details": "its green timbers"
}