{
  "reportId": "42885",
  "title": "Possible daytime highway crossing on US-90 outside Caryville",
  "date": "2003-10-15",
  "observed": "I was driving, I just crossed  river  about  200 yards back when in front of me it crossed  the highway. It was on all fours,  trying to look  different. It took about 4 to 5 seconds  to cross the  highway. It was dark, red long hair.",
  "classification": "Class B",
  "county": "Washington",
  "state": "Florida",
  "location": "-85.4937,30.46805",
  "location_details": "I was headed east on Highway 90 just came off river bridge"
}